color_parser_py-0.1.6.dist-info/METADATA
color_parser_py-0.1.6.dist-info/WHEEL
color_parser_py/py.typed
color_parser_py/__init__.py
color_parser_py/color_parser_py.pyi
color_parser_py/color_parser_py.cpython-39-aarch64-linux-gnu.so
color_parser_py-0.1.6.dist-info/RECORD
