Metadata-Version: 2.4
Name: color_parser_py
Version: 0.1.6
Classifier: Programming Language :: Rust
Classifier: Programming Language :: Python :: Implementation :: CPython
Classifier: Programming Language :: Python :: 3.7
Classifier: Programming Language :: Python :: 3.8
Classifier: Programming Language :: Python :: 3.9
Classifier: Programming Language :: Python :: 3.10
Classifier: Programming Language :: Python :: 3.11
Classifier: Programming Language :: Python :: 3.12
Classifier: Typing :: Typed
Summary: Python bindings for color parsing and conversion
Author-email: Aman Rusia <rusia.aman@gmail.com>
Requires-Python: >=3.7, <3.13
